{"allQuestionRecord":[{"id":36,"createdOn":"Mon, 31 Dec 2018 07:30:47 GMT","createdBy":3,"meetup":2,"title":"What is java development?","body":"I really love this topic...","votes":0},{"id":35,"createdOn":"Mon, 31 Dec 2018 05:57:52 GMT","createdBy":3,"meetup":2,"title":"What is java development?","body":"I really love this topic...","votes":0},{"id":34,"createdOn":"Mon, 31 Dec 2018 05:53:24 GMT","createdBy":3,"meetup":2,"title":"What is java development?","body":"I really love this topic...","votes":0},{"id":33,"createdOn":"Sun, 30 Dec 2018 17:22:05 GMT","createdBy":3,"meetup":2,"title":"What is java development?","body":"I really love this topic...","votes":0},{"id":32,"createdOn":"Sun, 30 Dec 2018 17:19:12 GMT","createdBy":2,"meetup":2,"title":"What is java development?","body":"I'm thinking...ohhhh","votes":0},{"id":31,"createdOn":"Sun, 30 Dec 2018 17:17:06 GMT","createdBy":3,"meetup":2,"title":"What is java development?","body":"I really love this topic...","votes":0},{"id":30,"createdOn":"Sun, 30 Dec 2018 17:03:00 GMT","createdBy":3,"meetup":2,"title":"What is java development?","body":"I really love this topic...","votes":0},{"id":29,"createdOn":"Sun, 30 Dec 2018 17:02:43 GMT","createdBy":3,"meetup":2,"title":"What is java development?","body":"I really love this topic...","votes":0},{"id":28,"createdOn":"Sun, 30 Dec 2018 17:01:18 GMT","createdBy":3,"meetup":2,"title":"What is java development?","body":"I really love this topic...","votes":0},{"id":27,"createdOn":"Sun, 30 Dec 2018 16:54:55 GMT","createdBy":3,"meetup":2,"title":"What is java development?","body":"I really love this topic...","votes":0},{"id":26,"createdOn":"Sun, 30 Dec 2018 16:49:09 GMT","createdBy":3,"meetup":2,"title":"What is java development?","body":"I really love this topic...","votes":0},{"id":25,"createdOn":"Sun, 30 Dec 2018 16:44:35 GMT","createdBy":3,"meetup":2,"title":"What is java development?","body":"I really love this topic...","votes":0},{"id":24,"createdOn":"Sun, 30 Dec 2018 16:43:47 GMT","createdBy":3,"meetup":2,"title":"What is java development?","body":"I really love this topic...","votes":0},{"id":23,"createdOn":"Sun, 30 Dec 2018 16:41:43 GMT","createdBy":3,"meetup":2,"title":"What is java development?","body":"I really love this topic...","votes":0},{"id":22,"createdOn":"Sun, 30 Dec 2018 16:38:52 GMT","createdBy":3,"meetup":2,"title":"What is java development?","body":"I really love this topic...","votes":0},{"id":21,"createdOn":"Sun, 30 Dec 2018 16:36:04 GMT","createdBy":3,"meetup":2,"title":"What is java development?","body":"I really love this topic...","votes":0},{"id":20,"createdOn":"Sun, 30 Dec 2018 16:35:17 GMT","createdBy":3,"meetup":2,"title":"What is java development?","body":"I really love this topic...","votes":0},{"id":19,"createdOn":"Sun, 30 Dec 2018 16:33:44 GMT","createdBy":3,"meetup":2,"title":"What is java development?","body":"I really love this topic...","votes":0},{"id":18,"createdOn":"Sun, 30 Dec 2018 16:25:54 GMT","createdBy":3,"meetup":2,"title":"What is java development?","body":"I really love this topic...","votes":0},{"id":17,"createdOn":"Sun, 30 Dec 2018 16:24:40 GMT","createdBy":3,"meetup":2,"title":"What is java development?","body":"I really love this topic...","votes":0},{"id":16,"createdOn":"Sun, 30 Dec 2018 16:22:53 GMT","createdBy":3,"meetup":2,"title":"What is java development?","body":"I really love this topic...","votes":0},{"id":15,"createdOn":"Sun, 30 Dec 2018 16:22:01 GMT","createdBy":3,"meetup":2,"title":"What is java development?","body":"I really love this topic...","votes":0},{"id":14,"createdOn":"Sun, 30 Dec 2018 16:21:35 GMT","createdBy":3,"meetup":2,"title":"What is java development?","body":"I really love this topic...","votes":0},{"id":13,"createdOn":"Sun, 30 Dec 2018 16:17:01 GMT","createdBy":3,"meetup":2,"title":"What is java development?","body":"I really love this topic...","votes":0},{"id":12,"createdOn":"Sun, 30 Dec 2018 16:10:47 GMT","createdBy":3,"meetup":2,"title":"What is java development?","body":"I really love this topic...","votes":0},{"id":11,"createdOn":"Sun, 30 Dec 2018 14:08:54 GMT","createdBy":3,"meetup":2,"title":"What is java development?","body":"I really love this topic...","votes":0},{"id":10,"createdOn":"Sun, 30 Dec 2018 12:49:26 GMT","createdBy":3,"meetup":2,"title":"What is java development?","body":"I really love this topic...","votes":0},{"id":9,"createdOn":"Sun, 30 Dec 2018 12:46:53 GMT","createdBy":3,"meetup":2,"title":"What is java development?","body":"I really love this topic...","votes":0},{"id":8,"createdOn":"Sun, 30 Dec 2018 12:46:20 GMT","createdBy":3,"meetup":2,"title":"What is java development?","body":"I really love this topic...","votes":0},{"id":7,"createdOn":"Sun, 30 Dec 2018 00:39:40 GMT","createdBy":3,"meetup":2,"title":"What is java development?","body":"I really love this topic...","votes":3},{"id":6,"createdOn":"Sun, 30 Dec 2018 00:33:12 GMT","createdBy":3,"meetup":2,"title":"What is java development?","body":"I really love this topic...","votes":0},{"id":5,"createdOn":"Sun, 30 Dec 2018 00:30:43 GMT","createdBy":3,"meetup":2,"title":"What is java development?","body":"I really love this topic...","votes":0},{"id":4,"createdOn":"Sun, 30 Dec 2018 00:29:34 GMT","createdBy":3,"meetup":2,"title":"What is java development?","body":"I really love this topic...","votes":0},{"id":3,"createdOn":"Sun, 30 Dec 2018 00:28:14 GMT","createdBy":3,"meetup":2,"title":"What is java development?","body":"I really love this topic...","votes":0},{"id":2,"createdOn":"Sat, 29 Dec 2018 21:15:05 GMT","createdBy":3,"meetup":2,"title":"What is RESTFul Api?","body":"I really love this topic...","votes":4},{"id":1,"createdOn":"Sat, 29 Dec 2018 20:33:37 GMT","createdBy":3,"meetup":2,"title":"What is java development?","body":"I really love this topic...","votes":8},{"id":0,"createdOn":"Sat, 29 Dec 2018 20:28:26 GMT","createdBy":3,"meetup":2,"title":"What is java development?","body":"I really love this topic...","votes":16}]}